AUTHORS
CHANGES.txt
INSTALL
LICENSE
MANIFEST.in
README.rst
REQUIRED
setup.cfg
setup.py
setup_utils.py
sequent/__init__.py
sequent.egg-info/PKG-INFO
sequent.egg-info/SOURCES.txt
sequent.egg-info/dependency_links.txt
sequent.egg-info/requires.txt
sequent.egg-info/top_level.txt
sequent/lib/__init__.py
sequent/lib/event.py
sequent/lib/main.py
sequent/lib/sequent_types.py
sequent/lib/step.py
sequent/lib/utils.py