Metadata-Version: 1.1
Name: sequent
Version: 3.1.7
Summary: sequent is a programming interface based on eventor providing simple way to write program flows
Home-page: https://github.com/Acrisel/sequent
Author: Acrisel Team
Author-email: support@acrisel.com
License: MIT
Keywords: framework workflow flow program dependency dependencies procedural procedure sequential recovery restart
Platform: UNKNOWN
Classifier: Development Status :: 5 - Production/Stable
Classifier: Environment :: Other Environment
Classifier: Intended Audience :: Developers
Classifier: License :: OSI Approved :: MIT License
Classifier: Operating System :: OS Independent
Classifier: Programming Language :: Python
Classifier: Programming Language :: Python :: 3
Classifier: Programming Language :: Python :: 3.2
Classifier: Programming Language :: Python :: 3.3
Classifier: Programming Language :: Python :: 3.4
Classifier: Programming Language :: Python :: 3.5
Classifier: Programming Language :: Python :: 3.6
Classifier: Topic :: Software Development :: Libraries :: Application Frameworks
